markups/__init__.py
markups/parser.py
pytelegrambotapi_markups-0.0.5.dist-info/LICENSE
pytelegrambotapi_markups-0.0.5.dist-info/METADATA
pytelegrambotapi_markups-0.0.5.dist-info/WHEEL
pytelegrambotapi_markups-0.0.5.dist-info/top_level.txt
pytelegrambotapi_markups-0.0.5.dist-info/RECORD
