Metadata-Version: 2.1
Name: pytelegrambotapi-markups
Version: 0.0.5
Summary: Handy markups for pyTelegramBotApi
Home-page: https://github.com/Mityuha/pyTelegramBotAPI_markups
Author: Dmitry Makarov
Author-email: mit.makaroff@gmail.com
License: GPL2
Keywords: markups pytelegrambotapi
Platform: UNKNOWN
Classifier: Programming Language :: Python :: 3.6
License-File: LICENSE
Requires-Dist: pyTelegramBotAPI
Requires-Dist: trafaret-config
